polars_mssql/__init__.py
polars_mssql/config.py
polars_mssql/connection.py
polars_mssql/connection_string.py
polars_mssql-0.3.dist-info/LICENSE
polars_mssql-0.3.dist-info/METADATA
polars_mssql-0.3.dist-info/WHEEL
polars_mssql-0.3.dist-info/top_level.txt
polars_mssql-0.3.dist-info/RECORD
