Metadata-Version: 2.1
Name: polars_mssql
Version: 0.3
Summary: Effortlessly connect to SQL Server to import data into Polars DataFrames and export data back to SQL Server.
Home-page: https://github.com/drosenman/py_mssql
Author: Dave Rosenman
Author-email: daverosenman@gmail.com
License: MIT
Project-URL: Bug Reports, https://github.com/drosenman/py_mssql/issues
Project-URL: Source, https://github.com/drosenman/py_mssql
Keywords: sql server polars sqlalchemy database
Classifier: Programming Language :: Python :: 3
Classifier: License :: OSI Approved :: MIT License
Classifier: Intended Audience :: Developers
Classifier: Topic :: Database
Requires-Python: >=3.7
License-File: LICENSE
Requires-Dist: polars
Requires-Dist: sqlalchemy
Requires-Dist: pyodbc
